kubeflow/__init__.py
kubeflow/katib/__init__.py
kubeflow/katib/api_client.py
kubeflow/katib/configuration.py
kubeflow/katib/rest.py
kubeflow/katib/api/__init__.py
kubeflow/katib/api/katib_client.py
kubeflow/katib/constants/__init__.py
kubeflow/katib/constants/constants.py
kubeflow/katib/models/__init__.py
kubeflow/katib/models/v1alpha3_algorithm_setting.py
kubeflow/katib/models/v1alpha3_algorithm_spec.py
kubeflow/katib/models/v1alpha3_collector_spec.py
kubeflow/katib/models/v1alpha3_early_stopping_setting.py
kubeflow/katib/models/v1alpha3_early_stopping_spec.py
kubeflow/katib/models/v1alpha3_experiment.py
kubeflow/katib/models/v1alpha3_experiment_condition.py
kubeflow/katib/models/v1alpha3_experiment_list.py
kubeflow/katib/models/v1alpha3_experiment_spec.py
kubeflow/katib/models/v1alpha3_experiment_status.py
kubeflow/katib/models/v1alpha3_feasible_space.py
kubeflow/katib/models/v1alpha3_file_system_path.py
kubeflow/katib/models/v1alpha3_filter_spec.py
kubeflow/katib/models/v1alpha3_go_template.py
kubeflow/katib/models/v1alpha3_graph_config.py
kubeflow/katib/models/v1alpha3_metric.py
kubeflow/katib/models/v1alpha3_metrics_collector_spec.py
kubeflow/katib/models/v1alpha3_nas_config.py
kubeflow/katib/models/v1alpha3_objective_spec.py
kubeflow/katib/models/v1alpha3_observation.py
kubeflow/katib/models/v1alpha3_operation.py
kubeflow/katib/models/v1alpha3_optimal_trial.py
kubeflow/katib/models/v1alpha3_parameter_assignment.py
kubeflow/katib/models/v1alpha3_parameter_spec.py
kubeflow/katib/models/v1alpha3_source_spec.py
kubeflow/katib/models/v1alpha3_suggestion.py
kubeflow/katib/models/v1alpha3_suggestion_condition.py
kubeflow/katib/models/v1alpha3_suggestion_list.py
kubeflow/katib/models/v1alpha3_suggestion_spec.py
kubeflow/katib/models/v1alpha3_suggestion_status.py
kubeflow/katib/models/v1alpha3_template_spec.py
kubeflow/katib/models/v1alpha3_trial.py
kubeflow/katib/models/v1alpha3_trial_assignment.py
kubeflow/katib/models/v1alpha3_trial_condition.py
prem_kubeflow_katib-0.0.1.dist-info/METADATA
prem_kubeflow_katib-0.0.1.dist-info/WHEEL
prem_kubeflow_katib-0.0.1.dist-info/top_level.txt
prem_kubeflow_katib-0.0.1.dist-info/RECORD
